dys_connector/__init__.py
dys_connector/dto.py
dys_connector/dys_api_manager.py
dys_connector/exceptions.py
dys_connector-0.2.32.dist-info/LICENSE
dys_connector-0.2.32.dist-info/METADATA
dys_connector-0.2.32.dist-info/WHEEL
dys_connector-0.2.32.dist-info/top_level.txt
dys_connector-0.2.32.dist-info/RECORD
