Metadata-Version: 2.1
Name: dys-connector
Version: 0.2.32
Summary: Logo DYS Connector API Python Implementation
Home-page: https://github.com/logo-group/dys-connector
Author: Mustafa Talha Arslan, Furkan Arif Bozdag, Hilal Ozkan
Author-email: mustafa.arslan@logo.com.tr, arif.bozdag@logo.com.tr, hilal.ozkan@logo.com.tr
License-File: LICENSE
Requires-Dist: requests
